LICENSE
MANIFEST.in
README.md
setup.cfg
setup.py
./src/deeptetrad/__init__.py
./src/deeptetrad/entry.py
./src/deeptetrad/pollen_train.py
./src/deeptetrad/tetrad_train.py
./src/deeptetrad/utils/__init__.py
./src/deeptetrad/utils/file_utils.py
./src/deeptetrad/utils/image_utils.py
./src/imgaug/__init__.py
./src/imgaug/imgaug.py
./src/imgaug/parameters.py
./src/imgaug/testutils.py
./src/imgaug/augmenters/__init__.py
./src/imgaug/augmenters/arithmetic.py
./src/imgaug/augmenters/blur.py
./src/imgaug/augmenters/color.py
./src/imgaug/augmenters/contrast.py
./src/imgaug/augmenters/convolutional.py
./src/imgaug/augmenters/flip.py
./src/imgaug/augmenters/geometric.py
./src/imgaug/augmenters/meta.py
./src/imgaug/augmenters/overlay.py
./src/imgaug/augmenters/segmentation.py
./src/imgaug/augmenters/size.py
./src/imgaug/augmenters/weather.py
./src/imgaug/external/__init__.py
./src/imgaug/external/opensimplex.py
./src/mrcnn/__init__.py
./src/mrcnn/config.py
./src/mrcnn/model.py
./src/mrcnn/parallel_model.py
./src/mrcnn/utils.py
./src/mrcnn/visualize.py
deeptetrad.egg-info/PKG-INFO
deeptetrad.egg-info/SOURCES.txt
deeptetrad.egg-info/dependency_links.txt
deeptetrad.egg-info/entry_points.txt
deeptetrad.egg-info/top_level.txt
src/imgaug/DejaVuSans.ttf
src/imgaug/quokka.jpg
src/imgaug/quokka_annotations.json
src/imgaug/quokka_depth_map_halfres.png